{"is_source_file": false, "format": "", "description": "", "external_files": [], "external_methods": [], "published": [], "classes": [], "methods": [], "calls": [], "search-terms": [], "state": 2, "file_id": 7, "knowledge_revision": 21, "git_revision": "6ac5b9099228a07358e394af8edcad2415d117b5", "hash": "d001d53c059625c4bcf75bf5a7f3fcf0", "format-version": 4, "code-base-name": "tic_tac_toe_frontend", "filename": "tic_tac_toe_frontend/package.json", "revision_history": [{"21": "6ac5b9099228a07358e394af8edcad2415d117b5"}]}